corpus_matcher/__init__.py
corpus_matcher/corpus_matcher.py
corpus_matcher-1.0.0.dist-info/licenses/LICENSE
corpus_matcher-1.0.0.dist-info/METADATA
corpus_matcher-1.0.0.dist-info/WHEEL
corpus_matcher-1.0.0.dist-info/top_level.txt
corpus_matcher-1.0.0.dist-info/RECORD
