Metadata-Version: 2.4
Name: corpus-matcher
Version: 1.0.0
Summary: Fast substring matching in large text corpora using optimized Levenshtein distance
Home-page: https://github.com/thiswillbeyourgithub/corpus_matcher
Keywords: string matching,levenshtein distance,text search,corpus search
Classifier: Development Status :: 3 - Alpha
Classifier: Intended Audience :: Developers
Classifier: License :: OSI Approved :: MIT License
Classifier: Operating System :: OS Independent
Classifier: Programming Language :: Python :: 3
Classifier: Programming Language :: Python :: 3.8
Classifier: Programming Language :: Python :: 3.9
Classifier: Programming Language :: Python :: 3.10
Classifier: Programming Language :: Python :: 3.11
Requires-Python: >=3.8
License-File: LICENSE
Requires-Dist: joblib
Requires-Dist: rapidfuzz
Dynamic: classifier
Dynamic: description
Dynamic: description-content-type
Dynamic: home-page
Dynamic: keywords
Dynamic: license-file
Dynamic: requires-dist
Dynamic: requires-python
Dynamic: summary
